pandas_pipeline_graphviz/__init__.py
pandas_pipeline_graphviz/logging_decorator.py
pandas_pipeline_graphviz/pipeline_graph.py
pandas_pipeline_graphviz-0.1.5.dist-info/METADATA
pandas_pipeline_graphviz-0.1.5.dist-info/WHEEL
pandas_pipeline_graphviz-0.1.5.dist-info/top_level.txt
pandas_pipeline_graphviz-0.1.5.dist-info/RECORD
