Metadata-Version: 2.1
Name: pandas-pipeline-graphviz
Version: 0.1.5
Summary: Pandas pipeline in graphviz
Home-page: https://github.com/qchenevier/pandas-pipeline-graphviz
Author: Quentin Chenevier
Author-email: qchenevier@users.noreply.github.com
License: UNKNOWN
Platform: UNKNOWN
Classifier: Programming Language :: Python :: 3
Classifier: License :: OSI Approved :: MIT License
Classifier: Operating System :: OS Independent
Requires-Python: >=3.6
Requires-Dist: pandas (>=1.0.0)
Requires-Dist: networkx (>=2.5)
Requires-Dist: addict (>=2.2)
